pt_seq/__init__.py
pt_seq/checker.py
pt_seq/processor.py
pt_seq/utils.py
pt_seq-0.0.6.dist-info/METADATA
pt_seq-0.0.6.dist-info/WHEEL
pt_seq-0.0.6.dist-info/licenses/LICENSE
pt_seq-0.0.6.dist-info/RECORD
